{"cameraMode":{"drawMode":0,"name":"Shaded","section":"Shading Mode"},"sceneLighting":true,"audioPlay":false,"sceneViewState":{"m_AlwaysRefresh":false,"showFog":true,"showSkybox":true,"showFlares":true,"showImageEffects":true,"showParticleSystems":true,"showVisualEffectGraphs":true,"m_FxEnabled":true},"in2DMode":false,"pivot":{"x":0.25,"y":-10.0,"z":-12.25},"rotation":{"x":-0.5016058087348938,"y":-0.05908380076289177,"z":0.034364502876996997,"w":-0.8623989224433899},"size":1.649002194404602,"orthographic":false}